nose_htmloutput-0.6.0.dist-info/DESCRIPTION.rst
nose_htmloutput-0.6.0.dist-info/METADATA
nose_htmloutput-0.6.0.dist-info/entry_points.txt
nose_htmloutput-0.6.0.dist-info/top_level.txt
nose_htmloutput-0.6.0.dist-info/RECORD
nose_htmloutput-0.6.0.dist-info/WHEEL
nose_htmloutput-0.6.0.dist-info/metadata.json
nose_htmloutput/__init__.py
nose_htmloutput/templates/report.html
