Metadata-Version: 1.1
Name: nose-htmloutput
Version: 0.6.0
Summary: Nose plugin that generates a nice html test report.
Home-page: https://github.com/ionelmc/nose-htmloutput
Author: Ionel Cristian Mărieș
Author-email: contact@ionelmc.ro
License: BSD
Platform: UNKNOWN
Classifier: Development Status :: 5 - Production/Stable
Classifier: Intended Audience :: Developers
Classifier: License :: OSI Approved :: BSD License
Classifier: Operating System :: Unix
Classifier: Operating System :: POSIX
Classifier: Operating System :: Microsoft :: Windows
Classifier: Programming Language :: Python
Classifier: Programming Language :: Python :: 2.6
Classifier: Programming Language :: Python :: 2.7
Classifier: Programming Language :: Python :: 3
Classifier: Programming Language :: Python :: 3.3
Classifier: Programming Language :: Python :: 3.4
Classifier: Programming Language :: Python :: Implementation :: CPython
Classifier: Programming Language :: Python :: Implementation :: PyPy
Classifier: Topic :: Utilities
